b.cp38-win_amd64.pyd
retina.cp38-win_amd64.pyd
retina_rf_generation.cp38-win_amd64.pyd
retina_rf_renegation.cp38-win_amd64.pyd
retina_sample.cp38-win_amd64.pyd
retina_utils.cp38-win_amd64.pyd
rf_generation.cp38-win_amd64.pyd
sample.cp38-win_amd64.pyd
utils.cp38-win_amd64.pyd
software_retina/__init__.pxd
software_retina/__init__.py
software_retina/retina.cp38-win_amd64.pyd
software_retina/rf_generation.cp38-win_amd64.pyd
software_retina/utils.cp38-win_amd64.pyd
software_retina/utils.pxd
software_retina_generation/__init__.py
software_retina_generation/fibonacci.py
software_retina_generation/ssnn.py
software_retina_generation/utils.py
src/__init__.pxd
src/__init__.py
src/retinavision/__init__.py
src/retinavision/retina.py
src/retinavision/rf_generation.py
src/retinavision/utils.py
src/software_retina/__init__.pxd
src/software_retina/__init__.py
src/software_retina/__init__.pyx
src/software_retina/retina.c
src/software_retina/retina.cp38-win_amd64.pyd
src/software_retina/retina.pyx
src/software_retina/rf_generation.c
src/software_retina/rf_generation.cp38-win_amd64.pyd
src/software_retina/rf_generation.pyx
src/software_retina/utils.c
src/software_retina/utils.cp38-win_amd64.pyd
src/software_retina/utils.pxd
src/software_retina/utils.pyx
src/software_retina_generation/__init__.py
src/software_retina_generation/fibonacci.py
src/software_retina_generation/ssnn.py
src/software_retina_generation/utils.py
software_retina-0.1.0.dist-info/LICENSE
software_retina-0.1.0.dist-info/METADATA
software_retina-0.1.0.dist-info/WHEEL
software_retina-0.1.0.dist-info/top_level.txt
software_retina-0.1.0.dist-info/RECORD
